skolo_shared/__init__.py
skolo_shared/models/__init__.py
skolo_shared/models/common/__init__.py
skolo_shared/models/common/base_model.py
skolo_shared/models/common/enums.py
skolo_shared/models/public/__init__.py
skolo_shared/models/public/permissions.py
skolo_shared/models/public/user.py
skolo_shared/models/tenant/__init__.py
skolo_shared/models/tenant/attendance.py
skolo_shared/models/tenant/classes.py
skolo_shared/models/tenant/events.py
skolo_shared/models/tenant/exam.py
skolo_shared/models/tenant/expenditure.py
skolo_shared/models/tenant/fee.py
skolo_shared/models/tenant/holiday.py
skolo_shared/models/tenant/parent.py
skolo_shared/models/tenant/payment.py
skolo_shared/models/tenant/school.py
skolo_shared/models/tenant/school_routine.py
skolo_shared/models/tenant/staff.py
skolo_shared/models/tenant/student.py
skolo_shared/models/tenant/subject.py
skolo_shared/models/tenant/timetable.py
skolo_shared/models/tenant/tracking.py
skolo_shared/models/tenant/transport.py
skolo_shared/models/tenant/user_file.py
skolo_shared/models/tenant/user_tenant_mapping.py
skolo_shared-0.0.36.dist-info/licenses/LICENSE
skolo_shared-0.0.36.dist-info/METADATA
skolo_shared-0.0.36.dist-info/WHEEL
skolo_shared-0.0.36.dist-info/top_level.txt
skolo_shared-0.0.36.dist-info/RECORD
