Metadata-Version: 2.4
Name: skolo-shared
Version: 0.0.36
Summary: Shared SQLAlchemy models for the School Management System
Home-page: https://github.com/skolo-cloud/skolo-shared
Author: Skolo Cloud
Author-email: Skolo Cloud <contact@skolo.cloud>
License: MIT
Project-URL: Homepage, https://github.com/skolo-cloud/skolo-shared
Project-URL: Repository, https://github.com/skolo-cloud/skolo-shared
Project-URL: Issues, https://github.com/skolo-cloud/skolo-shared/issues
Project-URL: Changelog, https://github.com/skolo-cloud/skolo-shared/blob/main/CHANGES.md
Keywords: sqlalchemy,orm,school-management,database,models
Classifier: Development Status :: 3 - Alpha
Classifier: Intended Audience :: Developers
Classifier: Programming Language :: Python :: 3
Classifier: Programming Language :: Python :: 3.10
Classifier: Programming Language :: Python :: 3.11
Classifier: Programming Language :: Python :: 3.12
Classifier: Topic :: Database
Classifier: Topic :: Software Development :: Libraries :: Python Modules
Requires-Python: >=3.10
License-File: LICENSE
Requires-Dist: SQLAlchemy>=2.0.0
Requires-Dist: psycopg2-binary>=2.9.0
Dynamic: author
Dynamic: home-page
Dynamic: license-file
Dynamic: requires-python
